MANIFEST.in
README.markdown
setup.py
django_transactional_cleanup/__init__.py
django_transactional_cleanup/apps.py
django_transactional_cleanup/models.py
django_transactional_cleanup/service.py
django_transactional_cleanup/signals.py
django_transactional_cleanup.egg-info/PKG-INFO
django_transactional_cleanup.egg-info/SOURCES.txt
django_transactional_cleanup.egg-info/dependency_links.txt
django_transactional_cleanup.egg-info/requires.txt
django_transactional_cleanup.egg-info/top_level.txt