Metadata-Version: 1.1
Name: django-transactional-cleanup
Version: 0.1.15
Summary: Deletes old files on transaction commit.
Home-page: https://github.com/jespino/django-transactional-cleanup
Author: Jesús Espino
Author-email: jesus.espino@kaleidos.net
License: MIT License
Download-URL: https://github.com/jespino/django-transactional-cleanup/tarball/master
Keywords: django
Platform: UNKNOWN
Classifier: Environment :: Web Environment
Classifier: Framework :: Django
Classifier: Intended Audience :: Developers
Classifier: Programming Language :: Python
Requires: python (>= 2.7)
Requires: django (>= 1.6.1)
